something_unique/__init__.py
something_unique/maths.py
something_unique-0.1.0.dist-info/LICENSE
something_unique-0.1.0.dist-info/METADATA
something_unique-0.1.0.dist-info/WHEEL
something_unique-0.1.0.dist-info/top_level.txt
something_unique-0.1.0.dist-info/RECORD
